drb_impl_xml/__init__.py
drb_impl_xml/_version.py
drb_impl_xml/cortex.yml
drb_impl_xml/xml_node.py
drb_impl_xml/xml_node_factory.py
drb_impl_xml-1.0.3.data/data/requirements.txt
drb_impl_xml-1.0.3.dist-info/METADATA
drb_impl_xml-1.0.3.dist-info/WHEEL
drb_impl_xml-1.0.3.dist-info/entry_points.txt
drb_impl_xml-1.0.3.dist-info/top_level.txt
drb_impl_xml-1.0.3.dist-info/RECORD
