Metadata-Version: 2.1
Name: drb-impl-xml
Version: 1.0.3
Summary: DRB XML implementation
Home-page: https://gitlab.com/drb-python/impl/xml
Author: GAEL Systems
Author-email: drb-python@gael.fr
License: UNKNOWN
Project-URL: Documentation, https://drb-python.gitlab.io/impl/xml
Project-URL: Source, https://gitlab.com/drb-python/impl/xml
Platform: UNKNOWN
Classifier: Programming Language :: Python :: 3.8
Classifier: License :: OSI Approved :: Apache Software License
Classifier: Operating System :: OS Independent
Requires-Python: >=3.8
Requires-Dist: drb (<1.1.0,>=1.0.1)
Requires-Dist: defusedxml (>=0.7.1)
